plex_mcp/__init__.py
plex_mcp/client/__init__.py
plex_mcp/client/plex_client.py
plex_mcp/sections/__init__.py
plex_mcp/sections/advanced_search.py
plex_mcp/sections/client_control.py
plex_mcp/sections/collections.py
plex_mcp/sections/movies.py
plex_mcp/sections/music.py
plex_mcp/sections/photo_library.py
plex_mcp/sections/settings.py
plex_mcp/sections/tv_shows.py
plex_mcp/sections/user_management.py
plex_mcp-0.2.0.dist-info/METADATA
plex_mcp-0.2.0.dist-info/WHEEL
plex_mcp-0.2.0.dist-info/entry_points.txt
plex_mcp-0.2.0.dist-info/licenses/LICENSE
plex_mcp-0.2.0.dist-info/RECORD
