Metadata-Version: 2.4
Name: plex-mcp
Version: 0.2.0
Summary: A MCP server to allow LLM's to interact with your plex server
License-File: LICENSE
Requires-Python: >=3.12
Requires-Dist: click>=8.3.0
Requires-Dist: fastmcp>=2.12.4
Requires-Dist: plexapi>=4.17.1
